simplebot_frotz/__init__.py
simplebot_frotz/game.py
simplebot_frotz/orm.py
simplebot_frotz-1.1.0.dist-info/LICENSE
simplebot_frotz-1.1.0.dist-info/METADATA
simplebot_frotz-1.1.0.dist-info/WHEEL
simplebot_frotz-1.1.0.dist-info/entry_points.txt
simplebot_frotz-1.1.0.dist-info/top_level.txt
simplebot_frotz-1.1.0.dist-info/RECORD
